yosina/__init__.py
yosina/chars.py
yosina/intrinsics.py
yosina/recipes.py
yosina/transliterator.py
yosina/types.py
yosina/transliterators/__init__.py
yosina/transliterators/circled_or_squared.py
yosina/transliterators/combined.py
yosina/transliterators/hira_kata.py
yosina/transliterators/hira_kata_composition.py
yosina/transliterators/hira_kata_table.py
yosina/transliterators/hyphens.py
yosina/transliterators/hyphens_data.py
yosina/transliterators/ideographic_annotations.py
yosina/transliterators/ivs_svs_base.py
yosina/transliterators/ivs_svs_base_data.py
yosina/transliterators/japanese_iteration_marks.py
yosina/transliterators/jisx0201_and_alike.py
yosina/transliterators/kanji_old_new.py
yosina/transliterators/mathematical_alphanumerics.py
yosina/transliterators/prolonged_sound_marks.py
yosina/transliterators/radicals.py
yosina/transliterators/roman_numerals.py
yosina/transliterators/spaces.py
yosina-1.0.0.dist-info/METADATA
yosina-1.0.0.dist-info/WHEEL
yosina-1.0.0.dist-info/RECORD
