Metadata-Version: 2.4
Name: yosina
Version: 1.0.0
Summary: Japanese text transliteration library
Project-URL: Homepage, https://github.com/yosina-lib/yosina
Project-URL: Repository, https://github.com/yosina-lib/yosina
Project-URL: Issues, https://github.com/yosina-lib/yosina/issues
Author-email: Moriyoshi Koizumi <mozo@mozo.jp>
License: MIT
Keywords: japanese,normalization,text-processing,transliteration
Classifier: Development Status :: 3 - Alpha
Classifier: Intended Audience :: Developers
Classifier: License :: OSI Approved :: MIT License
Classifier: Programming Language :: Python :: 3
Classifier: Programming Language :: Python :: 3.10
Classifier: Programming Language :: Python :: 3.11
Classifier: Programming Language :: Python :: 3.12
Classifier: Topic :: Software Development :: Libraries :: Python Modules
Classifier: Topic :: Text Processing :: Linguistic
Requires-Python: >=3.10
